inceptum/__init__.py
inceptum/config.py
inceptum/require.py
inceptum-0.5.0.dist-info/METADATA
inceptum-0.5.0.dist-info/WHEEL
inceptum-0.5.0.dist-info/top_level.txt
inceptum-0.5.0.dist-info/RECORD
