Metadata-Version: 2.4
Name: inceptum
Version: 0.5.0
Summary: Dependency Injection and Configuration
Author-email: Hans Gremmen <hans@leptonix.net>
License-Expression: MIT
Requires-Python: >=3.12
Requires-Dist: pyyaml>=6.0.0
